refstore/__init__.py
refstore/_async/__init__.py
refstore/_async/buckets.py
refstore/_async/file_service.py
refstore/core/__init__.py
refstore/core/config.py
refstore/core/exceptions.py
refstore/core/retry.py
refstore/sync/__init__.py
refstore/sync/buckets.py
refstore/sync/file_service.py
refstore/utils/__init__.py
refstore/utils/uri.py
refstore/web/__init__.py
refstore/web/app.py
refstore/web/models.py
refstore-0.2.1.dist-info/licenses/LICENSE
refstore-0.2.1.dist-info/METADATA
refstore-0.2.1.dist-info/WHEEL
refstore-0.2.1.dist-info/top_level.txt
refstore-0.2.1.dist-info/RECORD
