Metadata-Version: 2.4
Name: refstore
Version: 0.2.1
Summary: Simple and easy-to-use MinIO object storage service library
Author-email: RefStore Contributors <refstore@example.com>
Maintainer-email: RefStore Contributors <refstore@example.com>
License: MIT License
Project-URL: Homepage, https://github.com/yourusername/refstore
Project-URL: Documentation, https://github.com/yourusername/refstore#readme
Project-URL: Repository, https://github.com/yourusername/refstore
Project-URL: Issues, https://github.com/yourusername/refstore/issues
Keywords: minio,s3,object-storage,file-storage,cloud-storage,async,web-api,fastapi
Classifier: Development Status :: 3 - Alpha
Classifier: Intended Audience :: Developers
Classifier: License :: OSI Approved :: MIT License
Classifier: Operating System :: OS Independent
Classifier: Programming Language :: Python :: 3
Classifier: Programming Language :: Python :: 3.8
Classifier: Programming Language :: Python :: 3.9
Classifier: Programming Language :: Python :: 3.10
Classifier: Programming Language :: Python :: 3.11
Classifier: Programming Language :: Python :: 3.12
Classifier: Topic :: Software Development :: Libraries :: Python Modules
Classifier: Topic :: System :: Archiving :: Backup
Requires-Python: >=3.8
License-File: LICENSE
Requires-Dist: minio>=7.0.0
Requires-Dist: requests>=2.28.0
Provides-Extra: async
Requires-Dist: asyncio>=3.4.3; extra == "async"
Provides-Extra: web
Requires-Dist: fastapi>=0.100.0; extra == "web"
Requires-Dist: uvicorn>=0.23.0; extra == "web"
Requires-Dist: pydantic>=2.0.0; extra == "web"
Provides-Extra: dev
Requires-Dist: pytest>=7.0.0; extra == "dev"
Requires-Dist: pytest-asyncio>=0.21.0; extra == "dev"
Requires-Dist: pytest-cov>=4.0.0; extra == "dev"
Requires-Dist: black>=23.0.0; extra == "dev"
Requires-Dist: flake8>=6.0.0; extra == "dev"
Requires-Dist: mypy>=1.0.0; extra == "dev"
Requires-Dist: pre-commit>=3.0.0; extra == "dev"
Provides-Extra: all
Requires-Dist: refstore[async,dev,web]; extra == "all"
Dynamic: license-file
